LICENSE
MANIFEST.in
README.md
setup.py
withnewimplemenation11/__init__.py
withnewimplemenation11/api_helper.py
withnewimplemenation11/configuration.py
withnewimplemenation11/decorators.py
withnewimplemenation11/withnewimplemenation_11_client.py
withnewimplemenation11.egg-info/PKG-INFO
withnewimplemenation11.egg-info/SOURCES.txt
withnewimplemenation11.egg-info/dependency_links.txt
withnewimplemenation11.egg-info/requires.txt
withnewimplemenation11.egg-info/top_level.txt
withnewimplemenation11/controllers/__init__.py
withnewimplemenation11/controllers/base_controller.py
withnewimplemenation11/controllers/pet_controller.py
withnewimplemenation11/controllers/store_controller.py
withnewimplemenation11/controllers/user_controller.py
withnewimplemenation11/exceptions/__init__.py
withnewimplemenation11/exceptions/api_exception.py
withnewimplemenation11/http/__init__.py
withnewimplemenation11/http/http_call_back.py
withnewimplemenation11/http/http_client.py
withnewimplemenation11/http/http_context.py
withnewimplemenation11/http/http_method_enum.py
withnewimplemenation11/http/http_request.py
withnewimplemenation11/http/http_response.py
withnewimplemenation11/http/requests_client.py
withnewimplemenation11/models/__init__.py
withnewimplemenation11/models/api_response.py
withnewimplemenation11/models/category.py
withnewimplemenation11/models/o_auth_scope_enum.py
withnewimplemenation11/models/order.py
withnewimplemenation11/models/pet.py
withnewimplemenation11/models/status_1_enum.py
withnewimplemenation11/models/status_2_enum.py
withnewimplemenation11/models/status_enum.py
withnewimplemenation11/models/tag.py
withnewimplemenation11/models/user.py